cornsnipps/__init__.py
cornsnipps/time.py
cornsnipps/types.py
cornsnipps-0.0.5.dist-info/LICENSE
cornsnipps-0.0.5.dist-info/METADATA
cornsnipps-0.0.5.dist-info/WHEEL
cornsnipps-0.0.5.dist-info/top_level.txt
cornsnipps-0.0.5.dist-info/RECORD
